termuxmenu/__init__.py
termuxmenu/console.py
termuxmenu/default_console.py
termuxmenu/default_error.py
termuxmenu/default_interactive_menu.py
termuxmenu/default_menu.py
termuxmenu/encapsulate.py
termuxmenu/error.py
termuxmenu/inline_menu.py
termuxmenu/logger.py
termuxmenu/menu.py
termuxmenu/option_menu.py
termuxmenu/options_menu.py
termuxmenu/parser.py
termuxmenu/question.py
termuxmenu/selection_interactive_menu.py
termuxmenu/selection_menu.py
termuxmenu/sequential_menu.py
termuxmenu/string_generator.py
termuxmenu/validation_exception.py
termux_menu-0.0.5.dist-info/LICENSE
termux_menu-0.0.5.dist-info/METADATA
termux_menu-0.0.5.dist-info/WHEEL
termux_menu-0.0.5.dist-info/top_level.txt
termux_menu-0.0.5.dist-info/RECORD
